alalibo.py
setup.py
alalibo.egg-info/PKG-INFO
alalibo.egg-info/SOURCES.txt
alalibo.egg-info/dependency_links.txt
alalibo.egg-info/top_level.txt