Metadata-Version: 1.0
Name: alalibo
Version: 1.0.0
Summary: a module for nesting lists
Home-page: UNKNOWN
Author: alalibo_fiberesima
Author-email: fiberesimaalaliboralph@gmail.com
License: PSF
Platform: UNKNOWN
